cyclonedds.libs/libddsc-fc204970.so.0.10.5
cyclonedds.libs/libcycloneddsidl-b2f13d51.so.0.10.5
cyclonedds/__init__.py
cyclonedds/util.py
cyclonedds/__idlc__.py
cyclonedds/domain.py
cyclonedds/topic.py
cyclonedds/internal.py
cyclonedds/_idlpy.cpython-38-x86_64-linux-gnu.so
cyclonedds/_clayer.cpython-38-x86_64-linux-gnu.so
cyclonedds/core.py
cyclonedds/builtin.py
cyclonedds/qos.py
cyclonedds/pub.py
cyclonedds/py.typed
cyclonedds/dynamic.py
cyclonedds/__library__.py
cyclonedds/sub.py
cyclonedds/.libs/libddsc.so
cyclonedds/.libs/idlc
cyclonedds/tools/__init__.py
cyclonedds/tools/cli/__init__.py
cyclonedds/tools/cli/ls.py
cyclonedds/tools/cli/idl.py
cyclonedds/tools/cli/typeof.py
cyclonedds/tools/cli/utils.py
cyclonedds/tools/cli/qosformat.py
cyclonedds/tools/cli/main.py
cyclonedds/tools/cli/settings.py
cyclonedds/tools/cli/sub.py
cyclonedds/tools/cli/ddsperf.py
cyclonedds/tools/cli/ps.py
cyclonedds/tools/cli/data/__init__.py
cyclonedds/tools/cli/discovery/__init__.py
cyclonedds/tools/cli/discovery/ps_discoverables.py
cyclonedds/tools/cli/discovery/main.py
cyclonedds/tools/cli/discovery/ls_discoverables.py
cyclonedds/tools/cli/layout/__init__.py
cyclonedds/tools/cli/layout/ping.py
cyclonedds/tools/cli/layout/subscribe.py
cyclonedds/tools/cli/layout/app.py
cyclonedds/tools/cli/layout/publish.py
cyclonedds/tools/cli/layout/barchart.py
cyclonedds/tools/cli/layout/pong.py
cyclonedds/tools/pubsub/__init__.py
cyclonedds/tools/pubsub/check_entity_qos.py
cyclonedds/tools/pubsub/parse_qos.py
cyclonedds/tools/pubsub/datastruct.py
cyclonedds/tools/pubsub/entity_qos.py
cyclonedds/tools/pubsub/__main__.py
cyclonedds/tools/pubsub/topic_manager.py
cyclonedds/tools/ddsls/__init__.py
cyclonedds/tools/ddsls/__main__.py
cyclonedds/tools/wheel_idlc/__init__.py
cyclonedds/idl/__init__.py
cyclonedds/idl/mypy_plugin.py
cyclonedds/idl/annotations.py
cyclonedds/idl/_support.py
cyclonedds/idl/_builder.py
cyclonedds/idl/types.py
cyclonedds-0.10.5.dist-info/WHEEL
cyclonedds-0.10.5.dist-info/top_level.txt
cyclonedds-0.10.5.dist-info/entry_points.txt
cyclonedds-0.10.5.dist-info/RECORD
cyclonedds-0.10.5.dist-info/METADATA
cyclonedds-0.10.5.dist-info/LICENSE
