Metadata-Version: 2.1
Name: cyclonedds
Version: 0.10.5
Summary: Eclipse Cyclone DDS Python binding
Home-page: https://cyclonedds.io
Author: Eclipse Cyclone DDS Committers
Maintainer: Thijs Miedema
Maintainer-email: thijs.miedema@adlinktech.com
License: EPL-2.0, BSD-3-Clause
Project-URL: Documentation, https://cyclonedds.io/docs
Project-URL: Source Code, https://github.com/eclipse-cyclonedds/cyclonedds-python
Project-URL: Bug Tracker, https://github.com/eclipse-cyclonedds/cyclonedds-python/issues
Keywords: eclipse,cyclone,dds,pub,sub,pubsub,iot,cyclonedds,cdr,omg,idl,middleware,ros
Platform: Windows
Platform: Linux
Platform: Mac OS-X
Platform: Unix
Classifier: Development Status :: 5 - Production/Stable
Classifier: License :: OSI Approved :: Eclipse Public License 2.0 (EPL-2.0)
Classifier: Programming Language :: Python :: 3.7
Classifier: Programming Language :: Python :: 3.8
Classifier: Programming Language :: Python :: 3.9
Classifier: Programming Language :: Python :: 3.10
Classifier: Operating System :: OS Independent
Requires-Python: >=3.7
License-File: LICENSE
Requires-Dist: rich-click
Requires-Dist: typing-inspect >=0.6 ; python_version < "3.7"
Requires-Dist: typing-extensions >=3.7 ; python_version < "3.9"
Provides-Extra: dev
Requires-Dist: pytest >=6.2 ; extra == 'dev'
Requires-Dist: pytest-cov ; extra == 'dev'
Requires-Dist: pytest-mock ; extra == 'dev'
Requires-Dist: flake8 ; extra == 'dev'
Requires-Dist: flake8-bugbear ; extra == 'dev'
Requires-Dist: twine ; extra == 'dev'
Provides-Extra: docs
Requires-Dist: Sphinx >=4.0.0 ; extra == 'docs'
Requires-Dist: sphinx-rtd-theme >=0.5.2 ; extra == 'docs'
